{
  "component": "BadgeNetwork",
  "generatedAt": "2026-06-02T15:27:41.529Z",
  "projects": {
    "extension": {
      "filesScanned": 3162,
      "targetComponent": "BadgeNetwork",
      "mmds": {
        "totalInstances": 4,
        "filesCount": 1,
        "props": {
          "name": {
            "count": 4,
            "values": {
              "\"Ethereum\"": 4
            }
          },
          "src": {
            "count": 4,
            "values": {
              "\"https://assets.coingecko.com/coins/images/279/small/ethereum.png\"": 4
            }
          }
        }
      },
      "deprecated": {
        "totalInstances": 0,
        "filesCount": 0,
        "props": {}
      },
      "overall": {
        "totalInstances": 4,
        "filesCount": 1,
        "props": {
          "name": {
            "count": 4,
            "values": {
              "\"Ethereum\"": 4
            }
          },
          "src": {
            "count": 4,
            "values": {
              "\"https://assets.coingecko.com/coins/images/279/small/ethereum.png\"": 4
            }
          }
        }
      },
      "deprecatedByLegacyComponent": {}
    },
    "mobile": {
      "filesScanned": 6593,
      "targetComponent": "BadgeNetwork",
      "mmds": {
        "totalInstances": 2,
        "filesCount": 2,
        "props": {
          "src": {
            "count": 2,
            "values": {
              "{networkImage}": 2
            }
          }
        }
      },
      "deprecated": {
        "totalInstances": 8,
        "filesCount": 8,
        "props": {
          "name": {
            "count": 8,
            "values": {
              "{networkName}": 4,
              "{token.network?.shortName}": 1,
              "{normalizedNetworkChainId}": 1,
              "{depositNetworkName ?? networkName}": 1,
              "{position.chain}": 1
            }
          },
          "imageSource": {
            "count": 8,
            "values": {
              "{networkImageSource}": 5,
              "{getNetworkImageForToken(token)}": 1,
              "{NetworkBadgeSource(asset.chainId as `0x${string}`)}": 1,
              "{getNetworkImageSource({ chainId: caipChainId })}": 1
            }
          }
        }
      },
      "overall": {
        "totalInstances": 10,
        "filesCount": 10,
        "props": {
          "name": {
            "count": 8,
            "values": {
              "{networkName}": 4,
              "{token.network?.shortName}": 1,
              "{normalizedNetworkChainId}": 1,
              "{depositNetworkName ?? networkName}": 1,
              "{position.chain}": 1
            }
          },
          "imageSource": {
            "count": 8,
            "values": {
              "{networkImageSource}": 5,
              "{getNetworkImageForToken(token)}": 1,
              "{NetworkBadgeSource(asset.chainId as `0x${string}`)}": 1,
              "{getNetworkImageSource({ chainId: caipChainId })}": 1
            }
          },
          "src": {
            "count": 2,
            "values": {
              "{networkImage}": 2
            }
          }
        }
      },
      "deprecatedByLegacyComponent": {
        "BadgeNetwork": 8
      }
    }
  }
}
