{
  "generatedAt": "2026-05-18T08:08:59.419Z",
  "components": [
    {
      "component": "AvatarAccount",
      "file": "avataraccount-props-audit-latest.json",
      "projects": [
        "extension",
        "mobile"
      ],
      "generatedAt": "2026-05-18T07:55:52.743Z"
    },
    {
      "component": "AvatarBase",
      "file": "avatarbase-props-audit-latest.json",
      "projects": [
        "extension",
        "mobile"
      ],
      "generatedAt": "2026-05-18T07:56:21.305Z"
    },
    {
      "component": "AvatarFavicon",
      "file": "avatarfavicon-props-audit-latest.json",
      "projects": [
        "extension",
        "mobile"
      ],
      "generatedAt": "2026-05-18T07:56:50.007Z"
    },
    {
      "component": "AvatarGroup",
      "file": "avatargroup-props-audit-latest.json",
      "projects": [
        "extension",
        "mobile"
      ],
      "generatedAt": "2026-05-18T07:57:17.795Z"
    },
    {
      "component": "AvatarIcon",
      "file": "avataricon-props-audit-latest.json",
      "projects": [
        "extension",
        "mobile"
      ],
      "generatedAt": "2026-05-18T07:57:45.537Z"
    },
    {
      "component": "AvatarNetwork",
      "file": "avatarnetwork-props-audit-latest.json",
      "projects": [
        "extension",
        "mobile"
      ],
      "generatedAt": "2026-05-18T07:58:13.350Z"
    },
    {
      "component": "AvatarToken",
      "file": "avatartoken-props-audit-latest.json",
      "projects": [
        "extension",
        "mobile"
      ],
      "generatedAt": "2026-05-18T07:58:40.803Z"
    },
    {
      "component": "BadgeCount",
      "file": "badgecount-props-audit-latest.json",
      "projects": [
        "extension",
        "mobile"
      ],
      "generatedAt": "2026-05-18T07:59:08.337Z"
    },
    {
      "component": "BadgeNetwork",
      "file": "badgenetwork-props-audit-latest.json",
      "projects": [
        "extension",
        "mobile"
      ],
      "generatedAt": "2026-05-18T07:59:35.779Z"
    },
    {
      "component": "BadgeStatus",
      "file": "badgestatus-props-audit-latest.json",
      "projects": [
        "extension",
        "mobile"
      ],
      "generatedAt": "2026-05-18T08:00:03.409Z"
    },
    {
      "component": "BadgeWrapper",
      "file": "badgewrapper-props-audit-latest.json",
      "projects": [
        "extension",
        "mobile"
      ],
      "generatedAt": "2026-05-18T08:00:30.993Z"
    },
    {
      "component": "BottomSheetFooter",
      "file": "bottomsheetfooter-props-audit-latest.json",
      "projects": [
        "extension",
        "mobile"
      ],
      "generatedAt": "2026-05-18T08:00:58.298Z"
    },
    {
      "component": "BottomSheetOverlay",
      "file": "bottomsheetoverlay-props-audit-latest.json",
      "projects": [
        "extension",
        "mobile"
      ],
      "generatedAt": "2026-05-18T08:01:26.224Z"
    },
    {
      "component": "Box",
      "file": "box-props-audit-latest.json",
      "projects": [
        "extension",
        "mobile"
      ],
      "generatedAt": "2026-05-18T08:01:54.518Z"
    },
    {
      "component": "Button",
      "file": "button-props-audit-latest.json",
      "projects": [
        "extension",
        "mobile"
      ],
      "generatedAt": "2026-05-18T08:02:23.421Z"
    },
    {
      "component": "ButtonBase",
      "file": "buttonbase-props-audit-latest.json",
      "projects": [
        "extension",
        "mobile"
      ],
      "generatedAt": "2026-05-18T08:02:52.424Z"
    },
    {
      "component": "ButtonIcon",
      "file": "buttonicon-props-audit-latest.json",
      "projects": [
        "extension",
        "mobile"
      ],
      "generatedAt": "2026-05-18T08:03:20.803Z"
    },
    {
      "component": "Card",
      "file": "card-props-audit-latest.json",
      "projects": [
        "extension",
        "mobile"
      ],
      "generatedAt": "2026-05-18T08:03:49.084Z"
    },
    {
      "component": "Checkbox",
      "file": "checkbox-props-audit-latest.json",
      "projects": [
        "extension",
        "mobile"
      ],
      "generatedAt": "2026-05-18T08:04:17.262Z"
    },
    {
      "component": "HeaderBase",
      "file": "headerbase-props-audit-latest.json",
      "projects": [
        "extension",
        "mobile"
      ],
      "generatedAt": "2026-05-18T08:04:45.444Z"
    },
    {
      "component": "Icon",
      "file": "icon-props-audit-latest.json",
      "projects": [
        "extension",
        "mobile"
      ],
      "generatedAt": "2026-05-18T08:05:13.648Z"
    },
    {
      "component": "Input",
      "file": "input-props-audit-latest.json",
      "projects": [
        "extension",
        "mobile"
      ],
      "generatedAt": "2026-05-18T08:05:41.868Z"
    },
    {
      "component": "Label",
      "file": "label-props-audit-latest.json",
      "projects": [
        "extension",
        "mobile"
      ],
      "generatedAt": "2026-05-18T08:06:10.300Z"
    },
    {
      "component": "RadioButton",
      "file": "radiobutton-props-audit-latest.json",
      "projects": [
        "extension",
        "mobile"
      ],
      "generatedAt": "2026-05-18T08:06:38.474Z"
    },
    {
      "component": "Skeleton",
      "file": "skeleton-props-audit-latest.json",
      "projects": [
        "extension",
        "mobile"
      ],
      "generatedAt": "2026-05-18T08:07:06.620Z"
    },
    {
      "component": "Text",
      "file": "text-props-audit-latest.json",
      "projects": [
        "extension",
        "mobile"
      ],
      "generatedAt": "2026-05-18T08:07:35.001Z"
    },
    {
      "component": "TextButton",
      "file": "textbutton-props-audit-latest.json",
      "projects": [
        "extension",
        "mobile"
      ],
      "generatedAt": "2026-05-18T08:08:03.182Z"
    },
    {
      "component": "TextField",
      "file": "textfield-props-audit-latest.json",
      "projects": [
        "extension",
        "mobile"
      ],
      "generatedAt": "2026-05-18T08:08:31.434Z"
    },
    {
      "component": "Toast",
      "file": "toast-props-audit-latest.json",
      "projects": [
        "extension",
        "mobile"
      ],
      "generatedAt": "2026-05-18T08:08:59.416Z"
    }
  ]
}
